Changelog.md
MANIFEST.in
README.md
VERSION
setup.py
isdc_geoaccessibility/__init__.py
isdc_geoaccessibility.egg-info/PKG-INFO
isdc_geoaccessibility.egg-info/SOURCES.txt
isdc_geoaccessibility.egg-info/dependency_links.txt
isdc_geoaccessibility.egg-info/not-zip-safe
isdc_geoaccessibility.egg-info/top_level.txt
isdc_geoaccessibility/static/isdc_geoaccessibility/js/accessibility.min.js
isdc_geoaccessibility/static/isdc_geoaccessibility/js/addaccessibility.js