Metadata-Version: 1.0
Name: isdc-geoaccessibility
Version: 1.0.0
Summary: accesibility module
Home-page: UNKNOWN
Author: iMMAP
Author-email: asdc@immap.org
License: iMMAP
Platform: UNKNOWN
